{
  "project_info": {
    "project_number": "739297025304",
    "project_id": "my-musichat-app",
    "storage_bucket": "my-musichat-app.firebasestorage.app"
  },
  "client": [
    {
      "client_info": {
        "mobilesdk_app_id": "1:739297025304:android:282c3f716afef08ffad26d",
        "android_client_info": {
          "package_name": "com.example.musichat"
        }
      },
      "oauth_client": [],
      "api_key": [
        {
          "current_key": "AIzaSyCwBkhBzrnPOqdcMmXYac_LKgzt17KAzuk"
        }
      ],
      "services": {
        "appinvite_service": {
          "other_platform_oauth_client": []
        }
      }
    }
  ],
  "configuration_version": "1"
}